main.v
module top(A, D);

input [4:0] A;
output [31:0] D;

decoder5to32 U0(A, D);


endmodule

// 5-to-32 Decoder. 
module decoder5to32(A, D);

input [4:0] A;
output [31:0] D;

wire [11:0] W;

// Module Instantiations
decoder3to8 u0(.A(A[4:2]), .D(W[11:4]));
decoder2to4 u1(.A(A[1:0]), .D(W[3:0]));

// AND Gates
assign D[31] = W[11] & W[3];
assign D[30] = W[11] & W[2];
assign D[29] = W[11] & W[1];
assign D[28] = W[11] & W[0];

assign D[27] = W[10] & W[3];
assign D[26] = W[10] & W[2];
assign D[25] = W[10] & W[1];
assign D[24] = W[10] & W[0];

assign D[23] = W[9] & W[3];
assign D[22] = W[9] & W[2];
assign D[21] = W[9] & W[1];
assign D[20] = W[9] & W[0];

assign D[19] = W[8] & W[3];
assign D[18] = W[8] & W[2];
assign D[17] = W[8] & W[1];
assign D[16] = W[8] & W[0];

assign D[15] = W[7] & W[3];
assign D[14] = W[7] & W[2];
assign D[13] = W[7] & W[1];
assign D[12] = W[7] & W[0];

assign D[11] = W[6] & W[3];
assign D[10] = W[6] & W[2];
assign D[9] = W[6] & W[1];
assign D[8] = W[6] & W[0];

assign D[7] = W[5] & W[3];
assign D[6] = W[5] & W[2];
assign D[5] = W[5] & W[1];
assign D[4] = W[5] & W[0];

assign D[3] = W[4] & W[3];
assign D[2] = W[4] & W[2];
assign D[1] = W[4] & W[1];
assign D[0] = W[4] & W[0];

endmodule 


// 3-to-8 Decoder.
module decoder3to8(A, D);

input [2:0] A;
output [7:0] D;

wire [5:0] W;

decoder2to4 u0(.A(A[2:1]),  .D(W[5:2]));
decoder1to2 u1(.A(A[0]),    .D(W[1:0]));

// AND Gates
assign D[7] = W[5] & W[1];
assign D[6] = W[5] & W[0];
assign D[5] = W[4] & W[1];
assign D[4] = W[4] & W[0];
assign D[3] = W[3] & W[1];
assign D[2] = W[3] & W[0];
assign D[1] = W[2] & W[1];
assign D[6] = W[2] & W[0];


endmodule

// 2-to-4 Decoder.
module decoder2to4(A, D);

input [1:0] A;
output [3:0] D;

wire [3:0] W;

// Module Instantiations.

decoder1to2 u0(.A(A[1]), .D(W[3:2]));
decoder1to2 u1(.A(A[0]), .D(W[1:0]));

// AND Gates
assign D[3] = W[3] & W[1];
assign D[2] = W[3] & W[0];
assign D[1] = W[2] & W[1];
assign D[0] = W[2] & W[0];



endmodule


// 1-to-2 Decoder. 
module decoder1to2(A, D);

input A;
output [1:0] D;

assign D[1] = ~A;
assign D[0] = A;

endmodule

decoder3to8_tb.v
`timescale 1ns/1ns
`include "main.v"

module decoder3to8_tb;

reg [2:0] A;
wire [7:0] D;

decoder3to8 UUT (A, D); // instantiate the module

initial begin
    $dumpfile("decoder3to8.vcd");
    $dumpvars(0, decoder3to8_tb);
    
    A = 3'b000; #20;
    A = 3'b001; #20;
    A = 3'b010; #20;
    A = 3'b011; #20;
    A = 3'b100; #20;
    A = 3'b101; #20;
    A = 3'b110; #20;
    A = 3'b111; #20;
    
    
end


endmodule

decoder3to8.vcd
$date
	Fri Jun 28 16:23:16 2024
$end
$version
	Icarus Verilog
$end
$timescale
	1ns
$end
$scope module decoder3to8_tb $end
$var wire 8 ! D [7:0] $end
$var reg 3 " A [2:0] $end
$scope module UUT $end
$var wire 3 # A [2:0] $end
$var wire 8 $ D [7:0] $end
$var wire 6 % W [5:0] $end
$scope module u0 $end
$var wire 2 & A [1:0] $end
$var wire 4 ' W [3:0] $end
$var wire 4 ( D [3:0] $end
$scope module u0 $end
$var wire 1 ) A $end
$var wire 2 * D [1:0] $end
$upscope $end
$scope module u1 $end
$var wire 1 + A $end
$var wire 2 , D [1:0] $end
$upscope $end
$upscope $end
$scope module u1 $end
$var wire 1 - A $end
$var wire 2 . D [1:0] $end
$upscope $end
$upscope $end
$upscope $end
$enddefinitions $end
$comment Show the parameter values. $end
$dumpall
$end
#0
$dumpvars
b10 .
0-
b10 ,
0+
b10 *
0)
b1000 (
b1010 '
b0 &
b100010 %
b1000000z $
b0 #
b0 "
b1000000z !
$end
#20
b0x00000z !
b0x00000z $
b100001 %
b1 .
1-
b1 "
b1 #
#40
b100 (
b10000z !
b10000z $
b1001 '
b1 ,
1+
b1 &
b10010 %
b10 .
0-
b10 "
b10 #
#60
b1000z !
b1000z $
b10001 %
b1 .
1-
b11 "
b11 #
#80
b10 (
b100z !
b100z $
b1 *
1)
b110 '
b10 ,
0+
b10 &
b1010 %
b10 .
0-
b100 "
b100 #
#100
b10z !
b10z $
b1001 %
b1 .
1-
b101 "
b101 #
#120
b1 (
b1z !
b1z $
b101 '
b1 ,
1+
b11 &
b110 %
b10 .
0-
b110 "
b110 #
#140
b0x00000z !
b0x00000z $
b101 %
b1 .
1-
b111 "
b111 #
